{
    "DNDConfig": null,
    "__parentReadjusting__": false,
    "_height_": {
        "type": "string",
        "value": "360dp"
    },
    "_left_": {
        "type": "string",
        "value": "0dp"
    },
    "_margin_": [
        0,
        0,
        0,
        0
    ],
    "_padding_": [
        0,
        0,
        0,
        0
    ],
    "_skin_": "s1c8635da9b341c3b4c82f3f18dc05dd",
    "_top_": {
        "type": "string",
        "value": "175dp"
    },
    "_width_": {
        "type": "string",
        "value": "100%"
    },
    "allboxes": [],
    "allowHorizontalBounce": false,
    "allowVerticalBounce": false,
    "allowhorizontalbounce": false,
    "allowverticalbounce": false,
    "bounces": false,
    "canUpdateUI": true,
    "children": [
        "lblSep1",
        "lblSep2",
        "lblSep3",
        "lblSep4",
        "txtName",
        "txtEmail",
        "txtCompanyName",
        "lbxQuery",
        "FlexContainer09dd4938c815f44"
    ],
    "clipBounds": true,
    "clipbounds": true,
    "containerWeight": 100,
    "containerweight": 100,
    "decelerat": false,
    "decelerating": false,
    "dragg": false,
    "dragging": false,
    "enableScrolling": true,
    "enabled": false,
    "enablescrolling": true,
    "height": "360dp",
    "horizontalScrollIndicator": true,
    "horizontalscrollindicator": true,
    "id": "flexHelpDetails",
    "info": null,
    "isVisible": true,
    "isvisible": true,
    "kuid": "af4f3cebd4b64ffa86a073495b2c7b12",
    "layoutType": 2,
    "layouttype": 2,
    "left": "0dp",
    "margin": [
        0,
        0,
        0,
        0
    ],
    "name": "kony.ui.FlexScrollContainer",
    "orientation": 6,
    "padding": [
        0,
        0,
        0,
        0
    ],
    "pagingEnabled": false,
    "pagingenabled": false,
    "parent": "flexMain",
    "percent": true,
    "pf": "frmHelp",
    "render": true,
    "scrollDirection": 1,
    "scrolldirection": 1,
    "skin": "s1c8635da9b341c3b4c82f3f18dc05dd",
    "snapGridSize": 10,
    "snapToGrid": true,
    "snapgridsize": 10,
    "snaptogrid": true,
    "top": "175dp",
    "track": false,
    "tracking": false,
    "verticalScrollIndicator": true,
    "verticalscrollindicator": true,
    "wType": "FlexScrollContainer",
    "widgetAlignment": 1,
    "widgetalignment": 1,
    "width": "100%",
    "zIndex": 1,
    "zindex": 1
}