{
    "DNDConfig": null,
    "__parentReadjusting__": false,
    "_bottom_": {
        "type": "number",
        "value": "0"
    },
    "_height_": {
        "type": "string",
        "value": "100dp"
    },
    "_left_": {
        "type": "string",
        "value": "0dp"
    },
    "_margin_": [
        0,
        0,
        0,
        0
    ],
    "_padding_": [
        0,
        0,
        0,
        0
    ],
    "_render_": true,
    "_skin_": "sba031c311fd4e0e9221443a87423b87",
    "_top_": {
        "type": "string",
        "value": "0dp"
    },
    "_width_": {
        "type": "string",
        "value": "100%"
    },
    "allboxes": [],
    "autogrowMode": 0,
    "autogrowmode": 0,
    "bottom": 0,
    "canUpdateUI": true,
    "channel": "mobile",
    "children": [
        "flexPickup",
        "flexDestination",
        "CopyflexDropoffs025e68771ce4846"
    ],
    "clipBounds": true,
    "clipbounds": true,
    "containerWeight": 100,
    "containerweight": 100,
    "enableScrolling": true,
    "enabled": false,
    "enablescrolling": true,
    "height": "100dp",
    "id": "flexDetails",
    "info": null,
    "isVisible": true,
    "isvisible": true,
    "kuid": "a37d51ba11cb42f3b78c73360ba20553",
    "layoutType": 4,
    "layouttype": 4,
    "left": "0dp",
    "margin": [
        0,
        0,
        0,
        0
    ],
    "name": "kony.ui.FlexContainer",
    "orientation": 6,
    "padding": [
        0,
        0,
        0,
        0
    ],
    "parent": "flexMain",
    "percent": true,
    "pf": "frmConfirm",
    "render": true,
    "skin": "sba031c311fd4e0e9221443a87423b87",
    "snapGridSize": 10,
    "snapToGrid": true,
    "snapgridsize": 10,
    "snaptogrid": true,
    "top": "0dp",
    "wType": "FlexContainer",
    "widgetAlignment": 1,
    "widgetalignment": 1,
    "width": "100%",
    "zIndex": 2,
    "zindex": 2
}