{
    "@class": "com.kony.gen.viz.model.component.KVizImage2",
    "DNDConfig": null,
    "__parentReadjusting__": false,
    "_base64_": null,
    "_height_": {
        "type": "string",
        "value": "40dp"
    },
    "_margin_": [
        0,
        0,
        0,
        0
    ],
    "_padding_": [
        0,
        0,
        0,
        0
    ],
    "_right_": {
        "type": "string",
        "value": "10%"
    },
    "_skin_": "s4ea8d4d07574957b839f06194980e52",
    "_src_": "csmapicon.png",
    "_top_": {
        "type": "string",
        "value": "22dp"
    },
    "_width_": {
        "type": "string",
        "value": "40dp"
    },
    "base64": null,
    "canUpdateUI": true,
    "centerY": "50.00%",
    "centery": {
        "type": "string",
        "value": "50.00%"
    },
    "containerWeight": 100,
    "containerweight": 100,
    "context": {
        "channel": "mobile",
        "formID": "frmDebug",
        "templateType": "forms",
        "topLevelBox": null
    },
    "enabled": false,
    "height": "40dp",
    "id": "imgTickIcon6",
    "imageScaleMode": 1,
    "imagescalemode": 1,
    "info": null,
    "invokedProperty": "src",
    "isVisible": true,
    "isvisible": true,
    "kuid": "de6ffb7151714a9c8ff1c26820994d53",
    "margin": [
        0,
        0,
        0,
        0
    ],
    "name": "kony.ui.Image2",
    "padding": [
        0,
        0,
        0,
        0
    ],
    "parent": "flexRow6",
    "pf": "frmDebug",
    "render": true,
    "right": "10%",
    "skin": "s4ea8d4d07574957b839f06194980e52",
    "src": "csmapicon.png",
    "srcType": 1,
    "top": "22dp",
    "wType": "Image",
    "widgetAlignment": 5,
    "widgetalignment": 5,
    "width": "40dp",
    "zIndex": 1,
    "zindex": 1
}